kscanner/__init__.py
kscanner/scanners.py
kscanner-1.0.0.dist-info/LICENSE
kscanner-1.0.0.dist-info/METADATA
kscanner-1.0.0.dist-info/WHEEL
kscanner-1.0.0.dist-info/top_level.txt
kscanner-1.0.0.dist-info/RECORD
