Metadata-Version: 2.1
Name: kscanner
Version: 1.0.0
Summary: KScanner is a novel combination of DBSCAN and K-Means clustering that uses automated Epsilon and MinPts approximation
Home-page: https://github.com/DonutsDuncan/kscanner.git
Author: Peerapak Adsavakulchai, Duncan Calvert, and Charles Mudd
Author-email: duncanscalvert@gmail.com
Project-URL: Bug Tracker, https://github.com/DonutsDuncan/kscanner/issues
Project-URL: repository, https://github.com/DonutsDuncan/kscanner.git
Classifier: Programming Language :: Python :: 3
Classifier: License :: OSI Approved :: MIT License
Classifier: Operating System :: OS Independent
Requires-Python: >=3.6
License-File: LICENSE
